<templateSet group="PyQt">
  <template name="do gui widget" value="class Widget(QtWidgets.QWidget):&#10;    def __init__(self):&#10;        super().__init__()&#10;        self.resize(500, 500)" description="create class inherits from QtGui.QWidget" toReformat="false" toShortenFQNames="true">
    <context>
      <option name="Python" value="true" />
    </context>
  </template>
  <template name="do box" value="self.box = QtGui.QVBoxLayout(self)&#10;self.box.setMargin(0)&#10;self.box.setSpacing(0)" description="creates layout" toReformat="false" toShortenFQNames="true">
    <context>
      <option name="Python" value="true" />
    </context>
  </template>
  <template name="do gui bg" value="setStyleSheet(&quot;background-color: green&quot;)" description="create bacground" toReformat="false" toShortenFQNames="true">
    <context>
      <option name="Python" value="true" />
    </context>
  </template>
  <template name="do font" value="font = QtGui.QFont('Helvetica', 24, QtGui.QFont.Bold)&#10;self.setFont(font)" description="create and set Qfont" toReformat="false" toShortenFQNames="true">
    <context>
      <option name="Python" value="true" />
    </context>
  </template>
  <template name="do gui import" value="import sys&#10;from PyQt5 import QtWidgets" description="impor PyQt5" toReformat="false" toShortenFQNames="true">
    <context>
      <option name="Python" value="true" />
    </context>
  </template>
  <template name="do gui name" value="if __name__ == '__main__':&#10;    app = QtWidgets.QApplication(sys.argv)&#10;    # app.setStyleSheet(open('./etc/{0}.qss'.format('style'), &quot;r&quot;).read())&#10;    main = Widget()&#10;    main.show()&#10;    sys.exit(app.exec_())" description="create if __name__ == ... qt" toReformat="false" toShortenFQNames="true">
    <context>
      <option name="Python" value="true" />
    </context>
  </template>
  <template name="do setstyle file" value="app.setStyleSheet(open('{}'.format(css_path), &quot;r&quot;).read())" description="create setStyleSheet" toReformat="false" toShortenFQNames="true">
    <context>
      <option name="Python" value="true" />
    </context>
  </template>
</templateSet>